{"elitist": {"complexity_": 36, "error_": 0.19433590785223012, "fitness_": 68.11487707916774}, "config": {"early_stopping_delta": 0, "early_stopping_patience": -1, "matching_type": "NoneType", "n_initial_rules": 0, "n_iter": 32, "n_jobs": 1, "n_rules": 4, "random_state": "class:numpy.uint32", "rule_discovery__acceptance__beta": 1, "rule_discovery__acceptance": "class:suprb.optimizer.rule.acceptance.Variance", "rule_discovery__constraint__clip__bounds": "NoneType", "rule_discovery__constraint__clip": "class:suprb.optimizer.rule.constraint.Clip", "rule_discovery__constraint__min_range__min_range": 1e-06, "rule_discovery__constraint__min_range": "class:suprb.optimizer.rule.constraint.MinRange", "rule_discovery__constraint": "class:suprb.optimizer.rule.constraint.CombinedConstraint", "rule_discovery__fitness_objs": "tuple", "rule_discovery__fitness_objs_labels": "tuple", "rule_discovery__init__bounds": "NoneType", "rule_discovery__init__fitness": "class:suprb.rule.fitness.MooFitness", "rule_discovery__init__matching_type": "NoneType", "rule_discovery__init__model__alpha": 0.01, "rule_discovery__init__model__copy_X": true, "rule_discovery__init__model__fit_intercept": true, "rule_discovery__init__model__max_iter": "NoneType", "rule_discovery__init__model__positive": false, "rule_discovery__init__model__random_state": 42, "rule_discovery__init__model__solver": "auto", "rule_discovery__init__model__tol": 0.0001, "rule_discovery__init__model": "class:sklearn.linear_model._ridge.Ridge", "rule_discovery__init": "class:suprb.rule.initialization.MeanInit", "rule_discovery__lmbda": 60, "rule_discovery__mu": 44, "rule_discovery__mutation__matching_type": "NoneType", "rule_discovery__mutation__sigma": 1.3687643350018797, "rule_discovery__mutation": "class:suprb.optimizer.rule.mutation.Normal", "rule_discovery__n_iter": 2, "rule_discovery__n_jobs": 1, "rule_discovery__origin_generation__use_elitist": true, "rule_discovery__origin_generation": "class:suprb.optimizer.rule.origin.SquaredError", "rule_discovery__profile": false, "rule_discovery__random_state": "NoneType", "rule_discovery": "class:suprb.optimizer.rule.nsga2.nsga2.NSGA2", "solution_composition__archive": "class:suprb.optimizer.solution.archive.Elitist", "solution_composition__crossover__n": 3, "solution_composition__crossover": "class:suprb.optimizer.solution.ga.crossover.NPoint", "solution_composition__crossover_rate": 0.9, "solution_composition__elitist_ratio": 0.17, "solution_composition__init__fitness__alpha": 0.3, "solution_composition__init__fitness": "class:suprb.solution.fitness.ComplexityWu", "solution_composition__init__mixing__experience_calculation": "class:suprb.solution.mixing_model.ExperienceCalculation", "solution_composition__init__mixing__experience_weight": 1, "solution_composition__init__mixing__filter_subpopulation": "class:suprb.solution.mixing_model.FilterSubpopulation", "solution_composition__init__mixing": "class:suprb.solution.mixing_model.ErrorExperienceHeuristic", "solution_composition__init__p": 0.5, "solution_composition__init": "class:suprb.solution.initialization.RandomInit", "solution_composition__mutation": "class:suprb.optimizer.solution.ga.mutation.BitFlips", "solution_composition__mutation_rate": 0.001, "solution_composition__n_iter": 32, "solution_composition__n_jobs": 1, "solution_composition__population_size": 32, "solution_composition__random_state": "NoneType", "solution_composition__selection__k": 5, "solution_composition__selection": "class:suprb.optimizer.solution.ga.selection.Tournament", "solution_composition__warm_start": true, "solution_composition": "class:suprb.optimizer.solution.ga.base.GeneticAlgorithm", "verbose": 10}, "pool": [{"error_": 0.0001585437534726795, "experience_": 3.0, "match": {"bounds": "[[-0.9999999999999999, -0.9999999999999999], [-0.7037200798764277, 1.0], [-1.0, -1.0], [-1.0, 0.568282204857186], [-1.0, -0.2514847991114869]]"}, "is_fitted_": true, "model": {"coef_": "[0.0, -0.45368766514033637, 0.0, -0.7016863845949292, -0.2599599493403667]", "intercept_": -1.820722058252778}}, {"error_": 0.23227917650942265, "experience_": 530.0, "match": {"bounds": "[[-0.8773183296542543, 1.0000000000000002], [-1.0, 1.0], [-1.0, 0.6930457422980104], [-1.0, 1.0], [-1.0, 1.0000000000000002]]"}, "is_fitted_": true, "model": {"coef_": "[-1.6234704087658482, -0.7288171176859026, -1.2483737124229148, 0.2900976589277546, -1.1036702033611132]", "intercept_": -2.657756405347462}}, {"error_": 0.03998819335189083, "experience_": 10.0, "match": {"bounds": "[[-0.9999999999999999, -0.21526397931643307], [-1.0, -0.37355567440807413], [-1.0, -1.0], [-0.482176301922442, 0.4207390800659835], [-1.0, 1.0000000000000002]]"}, "is_fitted_": true, "model": {"coef_": "[3.1779428071061715, -0.026951896272613976, 0.0, 0.0, -0.0009904365586793596]", "intercept_": 3.05716752226422}}, {"error_": 0.1271059561800849, "experience_": 143.0, "match": {"bounds": "[[-0.9999999999999999, 1.0000000000000002], [-1.0, -0.10547475856926403], [0.9999999999999998, 0.9999999999999998], [-1.0, 1.0], [-1.0, 0.394191669165216]]"}, "is_fitted_": true, "model": {"coef_": "[-2.4085029775842024, -0.6301376410300826, 0.0, 0.27919179843655606, 1.857287849347397]", "intercept_": -0.9607590230685028}}, {"error_": 0.018217065068937367, "experience_": 28.0, "match": {"bounds": "[[-0.94196569879911, -0.80713803846993], [-1.0, 1.0], [0.9999999999999998, 0.9999999999999998], [-1.0, 0.1279039584694016], [-1.0, 1.0000000000000002]]"}, "is_fitted_": true, "model": {"coef_": "[-8.372864249790073, -0.05900620427934645, 2.3465556599793766e-28, 0.2919623262056053, 0.23716451643786354]", "intercept_": -6.981614693034999}}, {"error_": 0.24744647974157977, "experience_": 200.0, "match": {"bounds": "[[-0.9999999999999999, -0.03903978006395008], [-1.0, 1.0], [-0.7170678400248078, 0.9999999999999998], [-1.0, 1.0], [-0.8042481986640092, 0.48856842672461265]]"}, "is_fitted_": true, "model": {"coef_": "[-5.262282430480365, -0.5338630574090597, -0.46687424985284753, 0.4423818728798691, -0.7198181294396284]", "intercept_": -4.800981562287999}}, {"error_": 0.1286490478571676, "experience_": 42.0, "match": {"bounds": "[[-0.9350413661789772, -0.8706276383608045], [-1.0, 0.39920958210477686], [-1.0, 0.049326652418855366], [-0.6087314879975955, 0.9919652115806464], [-1.0, 0.3032517823526506]]"}, "is_fitted_": true, "model": {"coef_": "[0.4696537542204092, 0.6319937246492441, 0.2471422323594707, 0.11617883033778358, -1.1121750331851]", "intercept_": 0.7374917899631608}}, {"error_": 0.00018323547841228254, "experience_": 3.0, "match": {"bounds": "[[-0.4944101283354224, -0.18080321550180212], [0.36133477452258245, 1.0], [-0.8423652946380612, 0.8374851848768414], [-1.0, -0.5630837665716404], [-1.0, 1.0000000000000002]]"}, "is_fitted_": true, "model": {"coef_": "[-5.17689969051289e-31, -0.01569858829282343, -0.3168260546369852, 0.4151786519113817, -0.7646704984093408]", "intercept_": -2.253099592944387}}, {"error_": 0.0001, "experience_": 2.0, "match": {"bounds": "[[-0.9999999999999999, -0.9999999999999999], [-1.0, -0.2015391930958856], [-1.0, 0.9999999999999998], [-0.1354378611011309, 1.0], [-1.0, 0.2065732401329533]]"}, "is_fitted_": true, "model": {"coef_": "[0.0, 0.0, 0.0, 0.6202609543430994, -0.01956801977063801]", "intercept_": 1.377925332762559}}, {"error_": 0.010515597121232043, "experience_": 9.0, "match": {"bounds": "[[-0.9094161334893086, -0.661166553014544], [-1.0, -1.0], [-1.0, -1.0], [-1.0, 0.6020940833112175], [-1.0, 0.5136923970033811]]"}, "is_fitted_": true, "model": {"coef_": "[3.738730847810377, 0.0, 0.0, -0.34299918450424954, -0.00039343246146477935]", "intercept_": 3.593545383944484}}, {"error_": 0.0001, "experience_": 2.0, "match": {"bounds": "[[-0.9999999999999999, -0.9999999999999999], [-1.0, 0.21561926598094638], [0.9999999999999998, 0.9999999999999998], [-1.0, 0.08622825371564113], [-1.0, 0.35122605116654837]]"}, "is_fitted_": true, "model": {"coef_": "[0.0, 0.0, 0.0, 0.3014666691803245, -0.005503744865132016]", "intercept_": -0.8038960817333509}}, {"error_": 0.0293234593430185, "experience_": 32.0, "match": {"bounds": "[[-0.9305667153135879, 0.7856654616595893], [-1.0, -0.879122493761773], [-0.3837868389804278, 0.5356683201422279], [-1.0, 0.029145461727384303], [-1.0, 0.3432761209510662]]"}, "is_fitted_": true, "model": {"coef_": "[-2.64462383208797, 0.0, -0.6258828549178688, 0.43289020007286755, -0.01723024706330495]", "intercept_": -1.3238637917793274}}, {"error_": 0.09375099944607355, "experience_": 60.0, "match": {"bounds": "[[-0.4108947551737264, 1.0000000000000002], [-1.0, -0.332136803277989], [-1.0, -0.0690408297649277], [-1.0, 0.2446615713724315], [-1.0, -0.363428636867953]]"}, "is_fitted_": true, "model": {"coef_": "[-1.4339674860565608, -1.4848855898906894, -2.407238821071644, 0.3285716453601505, -0.010214967641686215]", "intercept_": -2.806804616412124}}, {"error_": 0.12528702095844646, "experience_": 206.0, "match": {"bounds": "[[-0.827002238346046, -0.06466345869394069], [-1.0, 1.0], [-1.0, 0.9999999999999998], [-1.0, 0.36931270129555105], [-0.9156243363801654, 1.0000000000000002]]"}, "is_fitted_": true, "model": {"coef_": "[-2.519290606591589, -0.14572284861546797, -0.6690010489720242, 0.3311273743672223, -1.3106426950180687]", "intercept_": -3.135355275819685}}, {"error_": 0.07689033323337946, "experience_": 112.0, "match": {"bounds": "[[-0.9999999999999999, -0.9369974952870116], [-1.0, -0.25920241486003964], [-1.0, 0.9999999999999998], [-0.638366290995882, 1.0], [-1.0, -0.6779269808340749]]"}, "is_fitted_": true, "model": {"coef_": "[14.009642014107564, 0.38321716274778284, 0.027943987311892255, 0.1506309264559977, 4.7797676534434155]", "intercept_": 18.327378296258438}}, {"error_": 0.002071591653510772, "experience_": 5.0, "match": {"bounds": "[[-0.9999999999999999, -0.9999999999999999], [-0.19138242141498946, 0.6660587908997095], [-0.7645097145734402, 0.9080203017710824], [0.18391359767320659, 1.0], [-0.865421333140356, 1.0000000000000002]]"}, "is_fitted_": true, "model": {"coef_": "[-3.549004607245794e-30, 0.8944597464266159, 0.3256276242024644, -0.3512803639839579, -1.0210874270669774]", "intercept_": 1.4618910050513438}}, {"error_": 0.17162649435663851, "experience_": 167.0, "match": {"bounds": "[[-0.9767893259211405, -0.7633906098281015], [-1.0, 0.4205954981582787], [-0.9636374865315058, 0.9999999999999998], [-0.8185226316647859, 0.7455754020056822], [-0.9316433532394253, 0.021715981176038124]]"}, "is_fitted_": true, "model": {"coef_": "[-4.8326571257099324, 0.3564074385549878, -0.3310386113284115, 0.1905741791799308, -1.1635600245629523]", "intercept_": -4.539171860150805}}, {"error_": 0.009045746154484518, "experience_": 9.0, "match": {"bounds": "[[-0.24894663894029767, 0.8823446175770585], [-1.0, 0.2813452626783586], [-1.0, -1.0], [-1.0, -0.48751178382096955], [-1.0, 0.33522464397466956]]"}, "is_fitted_": true, "model": {"coef_": "[-2.0343539822073975, -1.6146556708834359, 0.0, -0.15123129703734842, -1.1591312334536132]", "intercept_": -1.6707522605818284}}, {"error_": 0.060857378742079596, "experience_": 27.0, "match": {"bounds": "[[-0.9999999999999999, -0.6510896080054056], [-1.0, -1.0], [-1.0, 0.9999999999999998], [1.0, 1.0], [-1.0, 0.12683704253850892]]"}, "is_fitted_": true, "model": {"coef_": "[2.240972814781384, 0.0, -0.3721492155615784, 0.0, -0.38546156811698656]", "intercept_": 2.1083469369237102}}, {"error_": 0.17280019470368865, "experience_": 106.0, "match": {"bounds": "[[-0.9999999999999999, 0.0004920306596771784], [-1.0, 0.8813117450878213], [-1.0, 0.5896948599036896], [-1.0, -0.20533507076891472], [-0.25923911843097547, 1.0000000000000002]]"}, "is_fitted_": true, "model": {"coef_": "[-4.475013524634113, -0.4936943351772031, -0.7760896108595917, 0.809265230083847, -1.0720322564385227]", "intercept_": -3.991605725557892}}, {"error_": 0.0001, "experience_": 3.0, "match": {"bounds": "[[0.8911842278324449, 1.0000000000000002], [-1.0, 0.5593136212751303], [-1.0, 0.6438155883333225], [0.09138385477592248, 1.0], [-1.0, 0.6523557160209531]]"}, "is_fitted_": true, "model": {"coef_": "[0.0, -0.37715119430533967, -1.2381632304152763, 0.12990934444156874, -0.10846063479533072]", "intercept_": -2.0985779399413502}}, {"error_": 0.021027129426022927, "experience_": 70.0, "match": {"bounds": "[[-0.6136551096447675, 1.0000000000000002], [-1.0, 1.0], [-0.6663161487623133, 0.30949670664359374], [-1.0, 1.0], [-1.0, 0.21063429657786525]]"}, "is_fitted_": true, "model": {"coef_": "[-1.8546048810308768, -2.109921734636527, -1.1342862992799625, 0.3011530316351518, 0.1011376283361266]", "intercept_": -3.0538283625736207}}, {"error_": 0.00012379302125315727, "experience_": 3.0, "match": {"bounds": "[[-0.9999999999999999, -0.9999999999999999], [-0.3433658177926741, 1.0], [-0.8631460073396859, -0.7978689575819452], [-1.0, -0.019616032966992325], [-1.0, 0.04573320173890838]]"}, "is_fitted_": true, "model": {"coef_": "[0.0, -0.47563010069766004, 0.0, 0.5777993059523882, -0.6088027625519274]", "intercept_": 0.06284775929972397}}, {"error_": 0.3689934756316309, "experience_": 238.0, "match": {"bounds": "[[-0.9999999999999999, 1.0000000000000002], [-1.0, 0.12991947820932026], [-1.0, -0.045945263402277114], [0.039493368084990266, 1.0], [-1.0, -0.45936580920640835]]"}, "is_fitted_": true, "model": {"coef_": "[-1.1921326772599383, -0.7293193057264435, -1.2244328549405454, 0.2267445598810748, 0.5389480612454494]", "intercept_": -1.001920824755798}}, {"error_": 0.04575039593391131, "experience_": 109.0, "match": {"bounds": "[[-0.7002424059634869, 1.0000000000000002], [-1.0, -0.6273509233831552], [-0.6582409881328591, 0.9999999999999998], [-0.726496727508058, 1.0], [-0.9805805717473535, -0.8495438172968883]]"}, "is_fitted_": true, "model": {"coef_": "[-1.694980558855525, -1.7606480294955877, -0.8510322480009715, 0.3126357234932493, 1.6639762996801342]", "intercept_": -1.1110798723003983}}, {"error_": 0.1661762625920364, "experience_": 169.0, "match": {"bounds": "[[-0.9682347361904242, 0.028581011094256814], [-0.612507728954866, 0.6849534408395707], [-0.6104853268249553, 0.13773909295493902], [-1.0, 1.0], [-1.0, 0.9006168472312058]]"}, "is_fitted_": true, "model": {"coef_": "[-4.012911680011758, -0.8183277916115479, -1.0480113312053654, 0.3939392165494473, -0.8217090287051445]", "intercept_": -4.197618881320706}}, {"error_": 0.006947294515257922, "experience_": 7.0, "match": {"bounds": "[[-0.06801634146053115, 1.0000000000000002], [-1.0, 0.15359214178209876], [-1.0, -1.0], [-1.0, -0.5575650432933925], [-1.0, 1.0000000000000002]]"}, "is_fitted_": true, "model": {"coef_": "[-1.9356803315320736, -1.863611512525311, 0.0, -0.1710243969585672, -0.7072268423800087]", "intercept_": -1.5156097517419178}}, {"error_": 0.23349348491566407, "experience_": 108.0, "match": {"bounds": "[[-0.9999999999999999, -0.05909680289615271], [-0.6440489831442228, 1.0], [0.3832098654073453, 0.759910389674884], [-1.0, 1.0], [-1.0, 0.8111342343362814]]"}, "is_fitted_": true, "model": {"coef_": "[-4.508337250759606, 0.3066326508689658, 3.4108107584163356e-28, 0.4500636296368016, -0.87018379494022]", "intercept_": -4.0999195677203115}}, {"error_": 0.07318618476936545, "experience_": 40.0, "match": {"bounds": "[[-0.2984987686975421, 1.0000000000000002], [-1.0, 0.18669774215039542], [-1.0, 0.009336245071946914], [-0.09125670031647526, 1.0], [-1.0, 0.9859435684386906]]"}, "is_fitted_": true, "model": {"coef_": "[-1.1536596775431838, -1.40932615953389, -2.231525532368312, -0.0760702208662884, -0.699361783840769]", "intercept_": -3.22947394458786}}, {"error_": 0.02478538631360735, "experience_": 28.0, "match": {"bounds": "[[-0.9065351897937525, 0.322687280114315], [-1.0, -0.9033452376403978], [-0.7700436913245005, 0.4240152913573636], [-1.0, -0.33823152676732215], [-1.0, 0.740521933119619]]"}, "is_fitted_": true, "model": {"coef_": "[-2.464600120907598, 0.0, -1.3097709638948427, 0.48717359585488335, -0.10707660453994473]", "intercept_": -1.310829262288436}}, {"error_": 0.08815461332533081, "experience_": 29.0, "match": {"bounds": "[[-0.9999999999999999, -0.8535500699957876], [-0.8226861371600362, 0.540222767003057], [-1.0, -1.0], [-1.0, 0.05934848152411698], [-1.0, -0.20237705763257807]]"}, "is_fitted_": true, "model": {"coef_": "[11.734147457966117, 2.4258574075567827, 0.0, -0.6241475414478241, -1.3237900430343492]", "intercept_": 10.068275225135647}}, {"error_": 0.29895046949377313, "experience_": 108.0, "match": {"bounds": "[[-0.9999999999999999, -0.6920645799275218], [-1.0, -0.14763404397414193], [-1.0, 0.5169213520942005], [0.6618331788062934, 1.0], [-1.0, -0.5359081031852666]]"}, "is_fitted_": true, "model": {"coef_": "[-2.0552313039708054, -0.27573804786702694, -0.431687846617641, 0.0, 1.8526471963636972]", "intercept_": 0.37680357984240986}}, {"error_": 0.07174151831052047, "experience_": 120.0, "match": {"bounds": "[[-0.8526220794341902, 1.0000000000000002], [-0.5788412262398009, 0.22011851528570686], [-0.6136004032877742, 0.6288533795797355], [-1.0, 1.0], [-1.0, 1.0000000000000002]]"}, "is_fitted_": true, "model": {"coef_": "[-2.536968621788481, -1.502607796887067, -0.7869400866323762, 0.4069390531744876, -0.5153790986801476]", "intercept_": -3.409519466164695}}, {"error_": 0.04936982523609454, "experience_": 43.0, "match": {"bounds": "[[-0.6834596619432884, 0.6531272152034685], [-1.0, -0.15254245595904026], [-1.0, -0.27309464764332514], [-0.8108805487399504, 1.0], [-1.0, -0.9766220445172427]]"}, "is_fitted_": true, "model": {"coef_": "[-1.3483809882501252, -1.0042581754089122, -3.0210822463133598, 0.07437191181710041, -0.21586888694923642]", "intercept_": -3.1649315376008103}}, {"error_": 0.0001, "experience_": 1.0, "match": {"bounds": "[[-0.9797984797979796, -0.9797974797979797], [0.5675670675675676, 0.5675680675675675], [-1.0, -0.9999995], [0.202019702020202, 0.20202070202020198], [-0.4425191782185289, -0.44251817821852885]]"}, "is_fitted_": true, "model": {"coef_": "[0.0, 0.0, 0.0, 0.0, 0.0]", "intercept_": -1.3594042428876678}}, {"error_": 0.0001, "experience_": 1.0, "match": {"bounds": "[[-0.9696974696969696, -0.9696964696969697], [0.40540490540540547, 0.4054059054054055], [-0.4545459545454547, -0.4545449545454547], [0.9999995, 1.0], [0.4936990844450407, 0.4937000844450407]]"}, "is_fitted_": true, "model": {"coef_": "[0.0, 0.0, 0.0, 0.0, 0.0]", "intercept_": 0.8413215296354458}}], "input_space": "[[-0.9999999999999999, 1.0000000000000002], [-1.0, 1.0], [-1.0, 0.9999999999999998], [-1.0, 1.0], [-1.0, 1.0000000000000002]]"}