{"elitist": {"complexity_": 6, "error_": 0.061848778963972964, "fitness_": 88.89977920790375}, "config": {"early_stopping_delta": 0, "early_stopping_patience": -1, "matching_type": "NoneType", "n_initial_rules": 0, "n_iter": 32, "n_jobs": 1, "n_rules": 4, "random_state": "class:numpy.uint32", "rule_discovery__acceptance__beta": 1, "rule_discovery__acceptance": "class:suprb.optimizer.rule.acceptance.Variance", "rule_discovery__constraint__clip__bounds": "NoneType", "rule_discovery__constraint__clip": "class:suprb.optimizer.rule.constraint.Clip", "rule_discovery__constraint__min_range__min_range": 1e-06, "rule_discovery__constraint__min_range": "class:suprb.optimizer.rule.constraint.MinRange", "rule_discovery__constraint": "class:suprb.optimizer.rule.constraint.CombinedConstraint", "rule_discovery__fitness_objs": "tuple", "rule_discovery__fitness_objs_labels": "tuple", "rule_discovery__init__bounds": "NoneType", "rule_discovery__init__fitness": "class:suprb.rule.fitness.MooFitness", "rule_discovery__init__matching_type": "NoneType", "rule_discovery__init__model__alpha": 0.01, "rule_discovery__init__model__copy_X": true, "rule_discovery__init__model__fit_intercept": true, "rule_discovery__init__model__max_iter": "NoneType", "rule_discovery__init__model__positive": false, "rule_discovery__init__model__random_state": 42, "rule_discovery__init__model__solver": "auto", "rule_discovery__init__model__tol": 0.0001, "rule_discovery__init__model": "class:sklearn.linear_model._ridge.Ridge", "rule_discovery__init": "class:suprb.rule.initialization.MeanInit", "rule_discovery__lmbda": 36, "rule_discovery__mu": 36, "rule_discovery__mutation__matching_type": "NoneType", "rule_discovery__mutation__sigma": 2.4606949162377014, "rule_discovery__mutation": "class:suprb.optimizer.rule.mutation.Normal", "rule_discovery__n_iter": 1, "rule_discovery__n_jobs": 1, "rule_discovery__origin_generation__use_elitist": true, "rule_discovery__origin_generation": "class:suprb.optimizer.rule.origin.SquaredError", "rule_discovery__profile": false, "rule_discovery__random_state": "NoneType", "rule_discovery": "class:suprb.optimizer.rule.nsga2.nsga2.NSGA2", "solution_composition__archive": "class:suprb.optimizer.solution.archive.Elitist", "solution_composition__crossover__n": 3, "solution_composition__crossover": "class:suprb.optimizer.solution.ga.crossover.NPoint", "solution_composition__crossover_rate": 0.9, "solution_composition__elitist_ratio": 0.17, "solution_composition__init__fitness__alpha": 0.3, "solution_composition__init__fitness": "class:suprb.solution.fitness.ComplexityWu", "solution_composition__init__mixing__experience_calculation": "class:suprb.solution.mixing_model.ExperienceCalculation", "solution_composition__init__mixing__experience_weight": 1, "solution_composition__init__mixing__filter_subpopulation": "class:suprb.solution.mixing_model.FilterSubpopulation", "solution_composition__init__mixing": "class:suprb.solution.mixing_model.ErrorExperienceHeuristic", "solution_composition__init__p": 0.5, "solution_composition__init": "class:suprb.solution.initialization.RandomInit", "solution_composition__mutation": "class:suprb.optimizer.solution.ga.mutation.BitFlips", "solution_composition__mutation_rate": 0.001, "solution_composition__n_iter": 32, "solution_composition__n_jobs": 1, "solution_composition__population_size": 32, "solution_composition__random_state": "NoneType", "solution_composition__selection__k": 5, "solution_composition__selection": "class:suprb.optimizer.solution.ga.selection.Tournament", "solution_composition__warm_start": true, "solution_composition": "class:suprb.optimizer.solution.ga.base.GeneticAlgorithm", "verbose": 10}, "pool": [{"error_": 0.06403217118171332, "experience_": 4754.0, "match": {"bounds": "[[-1.0, 0.2645700426033103], [-1.0, 0.8574192949079227], [-1.0, 0.9943116935492907], [-0.9911528150134047, 1.0]]"}, "is_fitted_": true, "model": {"coef_": "[-2.203922818983226, -0.4303915655172522, 0.046497389371491275, -0.28246088461253444]", "intercept_": 0.0487804779317525}}, {"error_": 0.050418216401615444, "experience_": 2912.0, "match": {"bounds": "[[-0.31896403632895043, 0.40702628329209195], [-0.4060183504823116, 0.9999999999999998], [-0.6850453819546667, 0.782385446011877], [-0.15087415131776316, 1.0]]"}, "is_fitted_": true, "model": {"coef_": "[-1.7755926322407507, -0.5087685888721437, 0.28508575508959666, -0.28024048496824355]", "intercept_": 0.0324545581489063}}, {"error_": 0.0658542680897671, "experience_": 2443.0, "match": {"bounds": "[[-1.0, -0.1449174065606959], [-1.0, 0.9999999999999998], [-1.0, 1.0], [-0.9911528150134047, 0.8310902254183021]]"}, "is_fitted_": true, "model": {"coef_": "[-2.3790299725619737, -0.44178861737671277, -0.02823158280978169, -0.13780912148934277]", "intercept_": -0.08257746585654302}}, {"error_": 0.05609406146591652, "experience_": 1185.0, "match": {"bounds": "[[-1.0, 0.7081300246167934], [-1.0, 0.10904751697490336], [-1.0, -0.04987970988303539], [-0.9911528150134047, 1.0]]"}, "is_fitted_": true, "model": {"coef_": "[-2.2462540315138706, -0.589575160053357, 0.05300840447193394, -0.27117542592944]", "intercept_": -0.035616443242677265}}, {"error_": 0.05903190602595373, "experience_": 1757.0, "match": {"bounds": "[[-0.9066201585753122, 1.0000000000000002], [0.4670765316249974, 0.9999999999999998], [-1.0, 1.0], [-0.8721674981471877, 1.0]]"}, "is_fitted_": true, "model": {"coef_": "[-1.495031433706193, 0.15012981823498403, 0.11350124574680527, -0.3284488058200709]", "intercept_": -0.4429437240218781}}, {"error_": 0.0660034730492049, "experience_": 3461.0, "match": {"bounds": "[[-0.27221443286473135, 1.0000000000000002], [-1.0, 0.9999999999999998], [-1.0, 1.0], [-0.9911528150134047, 0.41349452373709794]]"}, "is_fitted_": true, "model": {"coef_": "[-1.5085756885177088, -0.4985730788608975, 0.27550981526835494, -0.23291191290955587]", "intercept_": 0.008508880933192575}}], "input_space": "[[-1.0, 1.0000000000000002], [-1.0, 0.9999999999999998], [-1.0, 1.0], [-0.9911528150134047, 1.0]]"}