{"elitist": {"complexity_": 21, "error_": 0.2550474917669517, "fitness_": 61.47380587606516}, "config": {"early_stopping_delta": 0, "early_stopping_patience": -1, "matching_type": "NoneType", "n_initial_rules": 0, "n_iter": 32, "n_jobs": 1, "n_rules": 4, "random_state": "class:numpy.uint32", "rule_discovery__acceptance__beta": 1, "rule_discovery__acceptance": "class:suprb.optimizer.rule.acceptance.Variance", "rule_discovery__constraint__clip__bounds": "NoneType", "rule_discovery__constraint__clip": "class:suprb.optimizer.rule.constraint.Clip", "rule_discovery__constraint__min_range__min_range": 1e-06, "rule_discovery__constraint__min_range": "class:suprb.optimizer.rule.constraint.MinRange", "rule_discovery__constraint": "class:suprb.optimizer.rule.constraint.CombinedConstraint", "rule_discovery__fitness_objs": "tuple", "rule_discovery__fitness_objs_labels": "tuple", "rule_discovery__init__bounds": "NoneType", "rule_discovery__init__fitness": "class:suprb.rule.fitness.MooFitness", "rule_discovery__init__matching_type": "NoneType", "rule_discovery__init__model__alpha": 0.01, "rule_discovery__init__model__copy_X": true, "rule_discovery__init__model__fit_intercept": true, "rule_discovery__init__model__max_iter": "NoneType", "rule_discovery__init__model__positive": false, "rule_discovery__init__model__random_state": 42, "rule_discovery__init__model__solver": "auto", "rule_discovery__init__model__tol": 0.0001, "rule_discovery__init__model": "class:sklearn.linear_model._ridge.Ridge", "rule_discovery__init": "class:suprb.rule.initialization.MeanInit", "rule_discovery__lmbda": 132, "rule_discovery__mu": 52, "rule_discovery__mutation__matching_type": "NoneType", "rule_discovery__mutation__sigma": 0.8502883535227292, "rule_discovery__mutation": "class:suprb.optimizer.rule.mutation.Normal", "rule_discovery__n_iter": 12, "rule_discovery__n_jobs": 1, "rule_discovery__origin_generation__use_elitist": true, "rule_discovery__origin_generation": "class:suprb.optimizer.rule.origin.SquaredError", "rule_discovery__profile": false, "rule_discovery__random_state": "NoneType", "rule_discovery": "class:suprb.optimizer.rule.nsga2.nsga2.NSGA2", "solution_composition__archive": "class:suprb.optimizer.solution.archive.Elitist", "solution_composition__crossover__n": 3, "solution_composition__crossover": "class:suprb.optimizer.solution.ga.crossover.NPoint", "solution_composition__crossover_rate": 0.9, "solution_composition__elitist_ratio": 0.17, "solution_composition__init__fitness__alpha": 0.3, "solution_composition__init__fitness": "class:suprb.solution.fitness.ComplexityWu", "solution_composition__init__mixing__experience_calculation": "class:suprb.solution.mixing_model.ExperienceCalculation", "solution_composition__init__mixing__experience_weight": 1, "solution_composition__init__mixing__filter_subpopulation": "class:suprb.solution.mixing_model.FilterSubpopulation", "solution_composition__init__mixing": "class:suprb.solution.mixing_model.ErrorExperienceHeuristic", "solution_composition__init__p": 0.5, "solution_composition__init": "class:suprb.solution.initialization.RandomInit", "solution_composition__mutation": "class:suprb.optimizer.solution.ga.mutation.BitFlips", "solution_composition__mutation_rate": 0.001, "solution_composition__n_iter": 32, "solution_composition__n_jobs": 1, "solution_composition__population_size": 32, "solution_composition__random_state": "NoneType", "solution_composition__selection__k": 5, "solution_composition__selection": "class:suprb.optimizer.solution.ga.selection.Tournament", "solution_composition__warm_start": true, "solution_composition": "class:suprb.optimizer.solution.ga.base.GeneticAlgorithm", "verbose": 10}, "pool": [{"error_": 0.02707378339298102, "experience_": 122.0, "match": {"bounds": "[[-0.7615716846960741, 0.7386354008504017], [-1.0, 0.7289976206349814], [-0.28022815215126073, 0.9999999999999998], [-1.0, 0.7681710793592917], [-1.0, 0.7678053550265651]]"}, "is_fitted_": true, "model": {"coef_": "[-1.9404116172244434, -1.60641397387848, -0.6403543630191809, 0.3844814985659495, -0.529040682355687]", "intercept_": -3.1645832041260187}}, {"error_": 0.19655931786138667, "experience_": 384.0, "match": {"bounds": "[[-0.7593579507135946, 1.0000000000000002], [-1.0, 0.9743396309972129], [-1.0, 0.9999999999999998], [-1.0, 1.0], [-1.0, 0.6692638344211214]]"}, "is_fitted_": true, "model": {"coef_": "[-1.567886902197253, -1.0785301214929652, -1.249661263998045, 0.256239747499026, -1.0657217260148297]", "intercept_": -2.7848358805795232}}, {"error_": 0.02786188462178934, "experience_": 40.0, "match": {"bounds": "[[-0.569625531659615, 1.0000000000000002], [-0.5952175073264679, 1.0], [-0.938181044472604, 0.9999999999999998], [-1.0, 1.0], [-1.0, 0.8770987436261292]]"}, "is_fitted_": true, "model": {"coef_": "[-1.7731681387738647, -0.31192233416089005, -0.6532196719905119, 0.26327772110353553, -0.884684228038715]", "intercept_": -2.93507881522583}}, {"error_": 0.030884850248646758, "experience_": 88.0, "match": {"bounds": "[[-0.6700356477969128, 1.0000000000000002], [-0.950017562592714, 0.24742619908748242], [-0.970108879333638, 0.9999999999999998], [-1.0, 0.548119221781489], [-1.0, 1.0000000000000002]]"}, "is_fitted_": true, "model": {"coef_": "[-2.250548491680416, -1.979371337010586, -0.8536953160886307, 0.3764229021449774, -0.3808443485768809]", "intercept_": -3.305337012004664}}, {"error_": 0.22382027388293407, "experience_": 235.0, "match": {"bounds": "[[-0.5360761207718524, 1.0000000000000002], [-1.0, 1.0], [-1.0, 0.9999999999999998], [-1.0, 1.0], [-1.0, 1.0000000000000002]]"}, "is_fitted_": true, "model": {"coef_": "[-1.4104177725535014, -0.945254427322008, -1.3003582523730985, 0.22985456000947607, -1.1853943324424012]", "intercept_": -2.7922079462650498}}, {"error_": 0.04875449460208703, "experience_": 158.0, "match": {"bounds": "[[-0.7419660850830405, 0.9496571531368827], [-1.0, 1.0], [-0.6105394181384662, 0.8383516025747482], [-1.0, 1.0], [-0.9517414165256602, 1.0000000000000002]]"}, "is_fitted_": true, "model": {"coef_": "[-2.1243515003708726, -1.7410117047782339, -0.7900605856357918, 0.3265679610835673, -0.3353862474536188]", "intercept_": -3.172345675644787}}, {"error_": 0.22801347129938251, "experience_": 611.0, "match": {"bounds": "[[-0.8767895086016957, 1.0000000000000002], [-1.0, 1.0], [-1.0, 0.9999999999999998], [-1.0, 1.0], [-1.0, 0.43262461776982086]]"}, "is_fitted_": true, "model": {"coef_": "[-1.594257580934268, -0.5899853141253026, -1.0630928576497105, 0.25649548506475517, -1.3258118963098982]", "intercept_": -2.614150599336732}}, {"error_": 0.03753045339585675, "experience_": 61.0, "match": {"bounds": "[[-0.8461671787996342, 1.0000000000000002], [-0.9460860439412802, 0.9025111091677062], [-0.5005814631690749, 0.9999999999999998], [-1.0, 0.26852864236949925], [-0.7715795764465652, 1.0000000000000002]]"}, "is_fitted_": true, "model": {"coef_": "[-2.071542047871647, -0.014296522094215813, -0.48884687366825624, 0.40059487561701834, -0.9066341327374364]", "intercept_": -2.9660045550551795}}, {"error_": 0.03352473428688094, "experience_": 164.0, "match": {"bounds": "[[-0.7105730131601131, 0.5079277624330351], [-1.0, 1.0], [-0.5815990581331554, 0.9999999999999998], [-1.0, 0.24697874375104678], [-1.0, 1.0000000000000002]]"}, "is_fitted_": true, "model": {"coef_": "[-2.089674334077918, -1.7287324240865, -0.7859196340655298, 0.3971192454741014, -0.39372765435036167]", "intercept_": -3.1215578686357386}}, {"error_": 0.2702416000733754, "experience_": 227.0, "match": {"bounds": "[[-0.9999999999999999, 1.0000000000000002], [-1.0, 1.0], [-0.7129764891923912, 0.9999999999999998], [-1.0, 1.0], [-0.7642476977941499, 1.0000000000000002]]"}, "is_fitted_": true, "model": {"coef_": "[-5.009744926892224, 0.37764903508639436, -0.5786912719432737, 0.4015955884673117, -1.244784080978392]", "intercept_": -4.667093446382276}}, {"error_": 0.03746099371761325, "experience_": 112.0, "match": {"bounds": "[[-0.5900070828301736, 1.0000000000000002], [-1.0, 0.6257793336529157], [-0.31542461194855553, 0.9999999999999998], [-1.0, 1.0], [-1.0, 1.0000000000000002]]"}, "is_fitted_": true, "model": {"coef_": "[-1.5867836391441614, -1.65142529120503, -0.6632233207057482, 0.30111403888936117, -0.4083521479364386]", "intercept_": -3.0439694594130584}}, {"error_": 0.1154321959230586, "experience_": 443.0, "match": {"bounds": "[[-0.9013446131113855, 1.0000000000000002], [-1.0, 1.0], [-0.7082517660198493, 0.9999999999999998], [-1.0, 1.0], [-1.0, 1.0000000000000002]]"}, "is_fitted_": true, "model": {"coef_": "[-2.3440379549021446, -1.321473004648349, -0.7919624376634494, 0.34999774262974426, -0.6794196789024731]", "intercept_": -3.108239233344824}}, {"error_": 0.0013408456843985383, "experience_": 3.0, "match": {"bounds": "[[-0.24890576539402218, 1.0000000000000002], [-0.0347919710145268, 1.0], [-1.0, 0.9999999999999998], [-1.0, 1.0], [-1.0, 1.0000000000000002]]"}, "is_fitted_": true, "model": {"coef_": "[0.0, 1.5705461159031497, 0.0, -0.8947299773405804, 0.706296622182442]", "intercept_": -0.9840493279103405}}, {"error_": 0.03256537221069427, "experience_": 97.0, "match": {"bounds": "[[-0.4616026781472119, 0.6852176537669495], [-1.0, 0.7973528259489882], [-0.7014467465604878, 0.9999999999999998], [-1.0, 1.0], [-1.0, 0.5741756092329938]]"}, "is_fitted_": true, "model": {"coef_": "[-1.7300619951459542, -1.875822425440904, -0.7704054023787881, 0.33123874735885184, -0.04221175083904384]", "intercept_": -2.917255452683902}}, {"error_": 0.062449733180557396, "experience_": 194.0, "match": {"bounds": "[[-0.8308343703301316, 1.0000000000000002], [-0.8660683896281024, 1.0], [-0.5527166521334048, 0.9999999999999998], [-0.8161522776912131, 1.0], [-1.0, 0.5532874761014259]]"}, "is_fitted_": true, "model": {"coef_": "[-2.3685954870206354, -2.1399394393919295, -0.8207411142842357, 0.38301421638362254, -0.03598359563638911]", "intercept_": -3.2031878922517194}}, {"error_": 0.22572793229576954, "experience_": 227.0, "match": {"bounds": "[[-0.9600025332942603, 1.0000000000000002], [-1.0, 1.0], [-1.0, 0.9570642300336754], [-1.0, 1.0], [-0.5727545412857361, 1.0000000000000002]]"}, "is_fitted_": true, "model": {"coef_": "[-3.6306001037738507, -0.2645517320900189, -1.1343236767561904, 0.253151598083648, -1.0712397234545703]", "intercept_": -3.9642017697301943}}, {"error_": 0.07904226008157535, "experience_": 94.0, "match": {"bounds": "[[-0.9668007382029358, 1.0000000000000002], [-1.0, 0.8299218169787703], [-1.0, 0.9999999999999998], [-1.0, 0.3763276308837833], [-0.3131546863448551, 1.0000000000000002]]"}, "is_fitted_": true, "model": {"coef_": "[-4.240634242142418, -1.0572661630156306, -1.6682683316146811, 0.4543934610435052, -0.9181723594695388]", "intercept_": -4.505976186014201}}, {"error_": 0.13005692153311418, "experience_": 127.0, "match": {"bounds": "[[-0.7656213286017542, 1.0000000000000002], [-0.4571113690149581, 1.0], [-1.0, 0.9999999999999998], [-1.0, 1.0], [-1.0, 1.0000000000000002]]"}, "is_fitted_": true, "model": {"coef_": "[-2.228001798776759, -0.05230747367434665, -1.1750816732580767, 0.3083833118976019, -1.1990592640976023]", "intercept_": -3.2570455760852375}}, {"error_": 0.2791050113561117, "experience_": 620.0, "match": {"bounds": "[[-0.9999999999999999, 1.0000000000000002], [-0.9122132181568706, 1.0], [-0.8576183060180089, 0.9999999999999998], [-1.0, 1.0], [-1.0, 0.31301446383406445]]"}, "is_fitted_": true, "model": {"coef_": "[-3.102138579085434, -0.9886151152928824, -0.6813710654090674, 0.33768304560916945, -0.25320571025631616]", "intercept_": -2.9681525050307904}}, {"error_": 0.0003081902791073865, "experience_": 3.0, "match": {"bounds": "[[0.10263516070740997, 1.0000000000000002], [-0.8652792568914223, 1.0], [-1.0, 0.9999999999999998], [-1.0, 0.7353306636336272], [-1.0, 1.0000000000000002]]"}, "is_fitted_": true, "model": {"coef_": "[-0.684920688203229, 0.29331969051377826, -1.4094582531181552, 1.245021456921037, -0.11090426551967544]", "intercept_": -1.424680764884735}}, {"error_": 0.0903370690140445, "experience_": 138.0, "match": {"bounds": "[[-0.851930445719671, 1.0000000000000002], [-1.0, 1.0], [-1.0, 0.9419781794462525], [-1.0, 1.0], [-0.6422751132570839, 1.0000000000000002]]"}, "is_fitted_": true, "model": {"coef_": "[-2.5005790384831394, -0.3146078991368705, -1.2347638123073552, 0.34537825458831034, -1.2231303448474617]", "intercept_": -3.340173938524299}}], "input_space": "[[-0.9999999999999999, 1.0000000000000002], [-1.0, 1.0], [-1.0, 0.9999999999999998], [-1.0, 1.0], [-1.0, 1.0000000000000002]]"}